aioelpris/__init__.py
aioelpris/core/const.py
aioelpris/core/models.py
aioelpris/pris.py
aioelpris-0.2.0.dist-info/LICENSE
aioelpris-0.2.0.dist-info/WHEEL
aioelpris-0.2.0.dist-info/METADATA
aioelpris-0.2.0.dist-info/RECORD
