Metadata-Version: 2.1
Name: aioelpris
Version: 0.2.0
Summary: An aio library to retrieve some Nordic countries current electricity price.
Home-page: https://github.com/dansmachina/aioelpris
License: Apache License
Author: Alejandro González Pérez
Author-email: 8874974+dansmachina@users.noreply.github.com
Requires-Python: >=3.9,<4.0
Classifier: License :: Other/Proprietary License
Classifier: Programming Language :: Python :: 3
Classifier: Programming Language :: Python :: 3.10
Classifier: Programming Language :: Python :: 3.9
Requires-Dist: aiohttp (>=3.8.1,<4.0.0)
Requires-Dist: pydantic (>=1.9.1,<2.0.0)
Project-URL: Repository, https://github.com/dansmachina/aioelpris
